LICENSE
README.md
setup.py
./__init__.py
./package.json
./skill.json
./version.py
./locale/en-us/dialog/add.meal.dialog
./locale/en-us/dialog/confirm.list.meals.dialog
./locale/en-us/dialog/confirm.remove.meal.dialog
./locale/en-us/dialog/failed.to.add.meal.dialog
./locale/en-us/dialog/failed.to.remove.meal.dialog
./locale/en-us/dialog/list.meals.dialog
./locale/en-us/dialog/meal.added.dialog
./locale/en-us/dialog/meal.removed.dialog
./locale/en-us/dialog/plan.meal.dialog
./locale/en-us/dialog/remove.meal.dialog
./locale/en-us/dialog/skip.list.meals.dialog
./locale/en-us/intents/add.meal.intent
./locale/en-us/intents/list.meal.intent
./locale/en-us/intents/plan.meal.intent
./locale/en-us/intents/remove.meal.intent
meal_plan_skill.egg-info/PKG-INFO
meal_plan_skill.egg-info/SOURCES.txt
meal_plan_skill.egg-info/dependency_links.txt
meal_plan_skill.egg-info/entry_points.txt
meal_plan_skill.egg-info/requires.txt
meal_plan_skill.egg-info/top_level.txt
test/test_main.py