Metadata-Version: 2.1
Name: meal-plan-skill
Version: 1.0.0
Home-page: https://github.com/mikejgray/skill-meal-plan
Author: Mike Gray
Author-email: mike@graywind.org
License: Apache-2.0
Keywords: ovos skill voice assistant
License-File: LICENSE
Requires-Dist: ovos-utils>=0.0.30,~=0.0
Requires-Dist: ovos-workshop>=0.0.12,~=0.0
Provides-Extra: test
Requires-Dist: ovos-plugin-manager; extra == "test"
Requires-Dist: pytest; extra == "test"
